setup.py
wecompush/__init__.py
wecompush/exceptions.py
wecompush/template_card.py
wecompush/wecompush.py
wecompush-0.0.2.dist-info/licenses/LICENSE
wecompush-0.0.2.dist-info/METADATA
wecompush-0.0.2.dist-info/WHEEL
wecompush-0.0.2.dist-info/top_level.txt
wecompush-0.0.2.dist-info/RECORD
