Metadata-Version: 2.4
Name: wecompush
Version: 0.0.2
Summary: 企业微信信息推送
Author-email: zhang3 <675942084@qq.com>
Classifier: Programming Language :: Python :: 3
Classifier: License :: OSI Approved :: MIT License
Classifier: Operating System :: OS Independent
Requires-Python: >=3.6
License-File: LICENSE
Dynamic: license-file
